{
    "mainSceneItems": {
        "Buttons": [
            {
                "name": "Users Managment",
                "id": "userMang",
                "listenerName": "userMang",
                "icon": "USER"
            },
            {
                "name": "Products Managment",
                "id": "productsMange",
                "listenerName": "productsMange",
                "icon": "SHOPPING_CART"
            },
            {
                "name": "Werehouse Managment",
                "id": "werehouseMange",
                "listenerName": "werehouseMange",
                "icon": "HOME"
            }

        ],
        "": ""
    },
    "leftSectionItems": {
        "userMang": {
            "sectionType": "",
            "items": [
                {
                    "name": "",
                    "id": "addUser",
                    "listinerName": "addUserForm",
                    "icon": "PLUS",
                    "fromName" : ""
                },
                {
                    "name": "",
                    "id": "existingUser",
                    "listinerName": "existingUserFrom",
                    "icon": "LIST_ALT",
                    "fromName" : ""
                }, 
                {
                    "name": "",
                    "id": "setingUsers",
                    "listinerName": "setingUsersForm",
                    "icon": "GEARS",
                    "fromName" : ""
                }
            ]
        },
        "productsMange": {
            "sectionType": "",
            "items": [
                {
                    "name": "",
                    "id": "",
                    "listinerName": "",
                    "icon": "PLUS",
                    "fromName" : ""
                }
            ]
        },
        "werehouseMange": {
            "sectionType": "",
            "items": [
                {
                    "name": "",
                    "id": "addWerehouse",
                    "listinerName": "",
                    "icon": "PLUS",
                    "fromName" : ""
                },
                {
                    "name": "",
                    "id": "",
                    "listinerName": "",
                    "icon": "PLUS",
                    "fromName" : ""
                }
            ]
        }
    },
    "databaseStroktur": {
        "databasName": "",
        "tables": [{
                "tableName": "",
                "columns": {
                    "id": {
                        "type": "",
                        "length": "",
                        "addtional": ""
                    }
                }
            }]
    }
}